bigquery_wrapper/__init__.py
bigquery_wrapper/bigquery_wrapper.py
bigquery_wrapper_gcp-0.0.6.dist-info/METADATA
bigquery_wrapper_gcp-0.0.6.dist-info/WHEEL
bigquery_wrapper_gcp-0.0.6.dist-info/top_level.txt
bigquery_wrapper_gcp-0.0.6.dist-info/RECORD
