Metadata-Version: 2.1
Name: bigquery-wrapper-gcp
Version: 0.0.6
Summary: Bigquery package
Author: Mithunan Sivakumar
Author-email: <mithunan@gmail.com>
Keywords: python
Classifier: Development Status :: 1 - Planning
Classifier: Intended Audience :: Developers
Classifier: Programming Language :: Python :: 3
Classifier: Operating System :: Unix
Classifier: Operating System :: MacOS :: MacOS X
Classifier: Operating System :: Microsoft :: Windows
Requires-Dist: google-auth
Requires-Dist: google-cloud-bigquery
